UnPAC/__init__.py
UnPAC/main.py
UnPAC-3.2.1.dist-info/LICENSE.txt
UnPAC-3.2.1.dist-info/METADATA
UnPAC-3.2.1.dist-info/WHEEL
UnPAC-3.2.1.dist-info/top_level.txt
UnPAC-3.2.1.dist-info/RECORD
