Metadata-Version: 2.1
Name: UnPAC
Version: 3.2.1
License-File: LICENSE.txt
Requires-Dist: setuptools
Requires-Dist: Pandas
Requires-Dist: zipp
Requires-Dist: dicom2nifti
Requires-Dist: pydicom
Requires-Dist: regex
